poetry_plugin_inspect/__init__.py
poetry_plugin_inspect/command.py
poetry_plugin_inspect/plugin.py
poetry_plugin_inspect/utils.py
poetry_plugin_inspect/webui/dist/favicon.svg
poetry_plugin_inspect/webui/dist/index.html
poetry_plugin_inspect-0.2.0.dist-info/METADATA
poetry_plugin_inspect-0.2.0.dist-info/WHEEL
poetry_plugin_inspect-0.2.0.dist-info/entry_points.txt
poetry_plugin_inspect-0.2.0.dist-info/RECORD
