Metadata-Version: 2.4
Name: poetry-plugin-inspect
Version: 0.2.0
Dynamic: Classifier
Summary: Poetry plugin that provide well detailed HTML report about available packages
Author-email: Abiodun Sotunde <sotundeabiodun00@gmail.com>
License: MIT
Keywords: dependencies tree,plugin,poetry,show dependencies
Requires-Python: <4.0,>=3.9
Requires-Dist: poetry<3.0.0,>=2.0
Requires-Dist: pydantic<3.0.0,>=2.10.6
Requires-Dist: requests<3.0.0,>=2.32.3
